gfhub/__init__.py
gfhub/client.py
gfhub/entry.py
gfhub/function.py
gfhub/gfhub.cpython-314-darwin.so
gfhub/nodes.py
gfhub/pipeline.py
gfhub/tags.py
gfhub-0.4.1.dist-info/METADATA
gfhub-0.4.1.dist-info/WHEEL
gfhub-0.4.1.dist-info/RECORD
