Metadata-Version: 2.4
Name: gfhub
Version: 0.4.1
Classifier: Programming Language :: Rust
Classifier: Programming Language :: Python :: Implementation :: CPython
Classifier: Programming Language :: Python :: Implementation :: PyPy
Requires-Dist: pandas>=2.0.3
Requires-Dist: pillow>=11.3.0
Requires-Dist: pyarrow>=17.0.0
Requires-Dist: python-dotenv>=1.0.0
Requires-Dist: pyyaml>=6.0.3
Requires-Dist: tqdm>=4.67.1
Requires-Dist: urllib3>=2.2.3
Requires-Dist: gdsfactory>=9.30.0 ; extra == 'dev'
Requires-Dist: ipykernel>=6.29.5 ; extra == 'dev'
Requires-Dist: ipywidgets>=8.1.7 ; extra == 'dev'
Requires-Dist: maturin>=1.9.6 ; extra == 'dev'
Requires-Dist: mkdocs>=1.6 ; extra == 'dev'
Requires-Dist: mkdocs-autorefs>=1.4 ; extra == 'dev'
Requires-Dist: mkdocs-shadcn>=0.2 ; extra == 'dev'
Requires-Dist: mkdocstrings[python]>=0.29 ; extra == 'dev'
Requires-Dist: nbconvert>=7.16 ; extra == 'dev'
Requires-Dist: papermill>=2.6 ; extra == 'dev'
Requires-Dist: pyright>=1.1.406 ; extra == 'dev'
Requires-Dist: pytest>=8.3.5 ; extra == 'dev'
Provides-Extra: dev
Home-Page: https://github.com/doplaydo/DataLab
Requires-Python: >=3.12
